{"version":"0.1.2","name":"bkjs-lmdb","description":"LMDB support for node.js and backendjs","main":"build/Release/binding","homepage":"https://github.com/vseryakov/backendjs","repository":"https://github.com/vseryakov/bkjs-lmdb","dependencies":{"nan":">= 2.0.9"},"engines":{"node":">= 0.10"},"license":"BSD-3-Clause","gypfile":true,"scripts":{"install":"node-gyp configure build"},"gitHead":"fbca68416fa06e9454625a2d2dd4a3a284800520","versions":[{"number":"0.1.0","date":"2015-10-15T03:41:13.820Z"},{"number":"0.1.2","date":"2016-03-09T19:22:02.530Z"}],"readme":"# LMDB module for node and backendjs\n\n# Usage\n\n```javascript\n  var lmdb = require(\"bkjs-lmb\");\n  var env = new bklmdb.Env({ path: \"/tmp\" });\n  var db = new lmdb.Database(env, { name: \"test\", flags: lmdb.MDB_CREATE }, function(err) {\n\n     this.put(\"key1\", \"value1\");\n     this.put(\"key2\", \"value2\");\n     this.select(\"key\", \"key\", { begins_with: 1 }, function(err, rows) {\n       console.log(rows);\n     });\n\n  });\n```\n\n## Env class\n - `new Env(options)` - create new environment\n - The options properties:\n   - path - the database file path\n   - flags - bitmask of LMDB_ flags\n   - dbs - number of databases\n## Database class\n- `new Database(env, options, callback)` - create new database object\n- Properties:\n  - open - 1 if the db is open\n  - name - the database file name\n- Methods:\n  - close - close the database\n  - drop - drop the database file\n  - get(key, callback) - return value for the given key\n  - put(key, value [, flags] [, callback]) - store a value for the given key\n  - incr(key, num [, flags] [, callback]) - increment a value by a number\n  - del(key [, value] [,callback]) - delete a key\n  - select(start, end [,flags] [, callback]) - return list of matching records\n    The flags are:\n     - desc - 1 to return in descendent order\n     - begins_with - 1 if match by beginning of the start key\n     - count - number of records to return\n\n# Author\n\nVlad Seryakov\n\n","created":"2015-10-15T03:41:13.820Z","modified":"2016-03-09T19:22:02.530Z","lastPublisher":{"name":"veryakov","email":"vseryakov@gmail.com"},"owners":[{"name":"veryakov","email":"vseryakov@gmail.com"}],"other":{"_attachments":{},"_from":".","_id":"bkjs-lmdb","_npmOperationalInternal":{"host":"packages-12-west.internal.npmjs.com","tmp":"tmp/bkjs-lmdb-0.1.2.tgz_1457551320052_0.2621312504634261"},"_npmUser":{"name":"veryakov","email":"vseryakov@gmail.com"},"_npmVersion":"1.4.29","_rev":"1-82a2c283d5fa7f8304c0129ad13d3c13","_shasum":"090e78d38386ec751fe4126d3f94471f1e7d2e1d","author":{"name":"Vlad Seryakov"},"bugs":{"url":"https://github.com/vseryakov/bkjs-lmdb/issues"},"directories":{},"dist-tags":{"latest":"0.1.2"},"dist":{"shasum":"090e78d38386ec751fe4126d3f94471f1e7d2e1d","tarball":"http://registry.npmjs.org/bkjs-lmdb/-/bkjs-lmdb-0.1.2.tgz"},"maintainers":[{"name":"veryakov","email":"vseryakov@gmail.com"}],"readmeFilename":"README.md","time":{"modified":"2016-03-09T19:22:02.530Z","created":"2015-10-15T03:41:13.820Z","0.1.0":"2015-10-15T03:41:13.820Z","0.1.2":"2016-03-09T19:22:02.530Z"}}}