{"name":"gc-watch","description":"Track node.js' garbage collection events and memory statistics","version":"0.1.1","repository":"https://github.com/sankha93/node-gc-watch","main":"index.js","license":"MIT","dependencies":{"bindings":"^1.2.1","nan":"^2.2.1"},"gypfile":true,"scripts":{"install":"node-gyp rebuild","test":"mocha --expose-gc"},"keywords":["gc","garbage","performance","memory","profile"],"devDependencies":{"mocha":"^2.4.5","should":"^8.3.1"},"gitHead":"a752401ac59f1f005e180c8fc43ee726e4d3d460","homepage":"https://github.com/sankha93/node-gc-watch#readme","versions":[{"number":"0.1.0","date":"2016-04-18T19:25:01.058Z"},{"number":"0.1.1","date":"2016-04-19T06:46:44.095Z"}],"readme":"# node-gc-watch [![Build Status](https://travis-ci.org/sankha93/node-gc-watch.svg?branch=master)](https://travis-ci.org/sankha93/node-gc-watch)\n\n`node-gc-watch` helps you attach your own event handlers to track when a GC is being fired in your Node.js application. Currently it provides a `beforeGC` and `afterGC` event.\n\n### Installation\n\n```\nnpm install gc-watch --save\n```\n\n### Usage\n\n```js\nvar gcWatch = require('gc-watch');\n\ngcWatch.on('beforeGC', function() {\n  // detect memory usage, push stats etc.\n});\n\ngcWatch.on('afterGC', function() {\n  // calculate memory freed by GC, etc.\n});\n```\n\n### License\n\nMIT\n","created":"2016-04-18T19:25:01.058Z","modified":"2016-04-19T06:46:44.095Z","lastPublisher":{"name":"sankha93","email":"sankha93@gmail.com"},"owners":[{"name":"sankha93","email":"sankha93@gmail.com"}],"other":{"_attachments":{},"_from":".","_id":"gc-watch","_nodeVersion":"4.3.0","_npmOperationalInternal":{"host":"packages-12-west.internal.npmjs.com","tmp":"tmp/gc-watch-0.1.1.tgz_1461048403646_0.37184497248381376"},"_npmUser":{"name":"sankha93","email":"sankha93@gmail.com"},"_npmVersion":"2.14.12","_rev":"1-913adf212aee03c9ad36fa74f017dacc","_shasum":"9e87a33deaf17c3bee8f418dba5ec301dedb1d8c","author":{"name":"Sankha Narayan Guria","email":"sankha93@gmail.com"},"bugs":{"url":"https://github.com/sankhs93/node-gc-memwatch.git"},"directories":{},"dist-tags":{"latest":"0.1.1"},"dist":{"shasum":"9e87a33deaf17c3bee8f418dba5ec301dedb1d8c","tarball":"http://registry.npmjs.org/gc-watch/-/gc-watch-0.1.1.tgz"},"maintainers":[{"name":"sankha93","email":"sankha93@gmail.com"}],"readmeFilename":"README.md","time":{"modified":"2016-04-19T06:46:44.095Z","created":"2016-04-18T19:25:01.058Z","0.1.0":"2016-04-18T19:25:01.058Z","0.1.1":"2016-04-19T06:46:44.095Z"}}}