{"name":"libarchive","version":"0.0.6","description":"NodeJS bindings to libarchive","main":"index.js","repository":"https://github.com/joaomoreno/node-libarchive","dependencies":{"node-pre-gyp":"^0.6.1","aws-sdk":"^2.0.31"},"devDependencies":{"async":"^0.9.0","mocha":"^2.0.1","temp":"^0.8.1"},"scripts":{"test":"mocha","install":"node-pre-gyp install --fallback-to-build"},"binary":{"module_name":"archive","module_path":"./lib","host":"https://node-libarchive.s3.amazonaws.com/"},"keywords":["libarchive"],"license":"MIT","gypfile":true,"gitHead":"1f9d3cf41f2d5c487b65b5f44cf030dded223df0","homepage":"https://github.com/joaomoreno/node-libarchive","bundleDependencies":["node-pre-gyp"],"versions":[{"number":"0.0.1","date":"2014-12-11T21:42:17.039Z"},{"number":"0.0.2","date":"2014-12-14T11:34:44.218Z"},{"number":"0.0.3","date":"2014-12-16T16:19:46.749Z"},{"number":"0.0.4","date":"2014-12-17T10:08:00.041Z"},{"number":"0.0.5","date":"2014-12-17T10:12:02.720Z"},{"number":"0.0.6","date":"2015-02-02T09:06:11.486Z"}],"readme":"# Install\r\n\r\n\tnpm install libarchive\r\n\r\n# Build\r\n\r\n## All platforms\r\n\r\n\tgit submodule update --init\r\n\tnpm install\r\n\r\n## OS X\r\n\r\n\tcd deps/libarchive\r\n\tcmake .\r\n\tmake archive_static\r\n\tcd ../..\r\n\t./node_modules/.bin/node-pre-gyp rebuild\r\n\r\n## Linux\r\n\r\n\tcd deps/libarchive\r\n\tcmake .\r\n\r\nEdit `deps/libarchive/libarchive/CMakeFiles/archive_static.dir/flags.make` and add `-fPIC` to `CFLAGS`.\r\n\r\n\tmake archive_static\r\n\tcd ../..\r\n\t./node_modules/.bin/node-pre-gyp rebuild\r\n\r\n## Windows (x64)\r\n\r\nPowershell:\r\n\r\n\t$MSBUILD=\"${env:ProgramFiles(x86)}\\MSBuild\\12.0\\Bin\\MSBuild\"\r\n\r\n\tpushd deps\\zlib-win64\r\n\t.$MSBUILD /p:Platform=x64 /p:Configuration=Release zlib.msvs2013.vcxproj\r\n\tpopd\r\n\r\n\tpushd deps\\libarchive\r\n\tcmake -A x64 -G \"Visual Studio 12 2013\" -D ZLIB_LIBRARY=..\\zlib-win64\\x64\\Release\\zlib.lib -D ZLIB_INCLUDE_DIR=..\\zlib-win64 .\r\n\t.$MSBUILD /p:Configuration=Release libarchive\\archive_static.vcxproj\r\n\tpopd\r\n\r\n\t.\\node_modules\\.bin\\node-pre-gyp rebuild\r\n\r\n## Windows (ia32)\r\n\r\nPowershell:\r\n\r\n\t$MSBUILD=\"${env:ProgramFiles(x86)}\\MSBuild\\12.0\\Bin\\MSBuild\"\r\n\r\n\tpushd deps\\zlib-win64\r\n\t.$MSBUILD /p:Platform=win32 /p:Configuration=Release zlib.msvs2013.vcxproj\r\n\tpopd\r\n\r\n\tpushd deps\\libarchive\r\n\tcmake -A win32 -G \"Visual Studio 12 2013\" -D ZLIB_LIBRARY=..\\zlib-win64\\Release\\zlib.lib -D ZLIB_INCLUDE_DIR=..\\zlib-win64 .\r\n\t.$MSBUILD /p:Configuration=Release libarchive\\archive_static.vcxproj\r\n\tpopd\r\n\r\n\t.\\node_modules\\.bin\\node-pre-gyp --target_arch=ia32 rebuild\r\n","created":"2014-12-11T21:42:17.039Z","modified":"2015-02-02T09:06:11.486Z","lastPublisher":{"name":"joaomoreno","email":"mail@joaomoreno.com"},"owners":[{"name":"joaomoreno","email":"mail@joaomoreno.com"}],"other":{"_attachments":{},"_from":".","_id":"libarchive","_nodeVersion":"0.10.33","_npmUser":{"name":"joaomoreno","email":"mail@joaomoreno.com"},"_npmVersion":"2.1.11","_rev":"1-2e95e6c0923131e37ded59ae65c2909f","_shasum":"c63cbeaa005f57be5e379cb7f8606dca3e970cbc","author":{"name":"João Moreno"},"bugs":{"url":"https://github.com/joaomoreno/node-libarchive/issues"},"directories":{"test":"test"},"dist-tags":{"latest":"0.0.6"},"dist":{"shasum":"c63cbeaa005f57be5e379cb7f8606dca3e970cbc","tarball":"http://registry.npmjs.org/libarchive/-/libarchive-0.0.6.tgz"},"maintainers":[{"name":"joaomoreno","email":"mail@joaomoreno.com"}],"readmeFilename":"README.md","time":{"modified":"2015-02-02T09:06:11.486Z","created":"2014-12-11T21:42:17.039Z","0.0.1":"2014-12-11T21:42:17.039Z","0.0.2":"2014-12-14T11:34:44.218Z","0.0.3":"2014-12-16T16:19:46.749Z","0.0.4":"2014-12-17T10:08:00.041Z","0.0.5":"2014-12-17T10:12:02.720Z","0.0.6":"2015-02-02T09:06:11.486Z"}}}