{"name":"nodesolve","version":"0.1.0-alpha-1","description":"Use [LP Solve](http://lpsolve.sourceforge.net) from NodeJs. This module uses LP Solve 5.5.2","main":"index.js","scripts":{"test":"gulp test","preinstall":"node-gyp configure && node-gyp rebuild"},"keywords":["lpsolve","lp_solve","lp","solve","linear","programming","math"],"repository":"https://github.com/rubenjgarcia/nodesolve","license":"MIT","dependencies":{"bindings":"^1.2.1","lodash":"^4.5.0","nan":"^2.2.0"},"devDependencies":{"expect.js":"^0.3.1","gulp":"^3.9.1","gulp-coverage":"^0.3.38","gulp-jsdoc3":"^0.2.0","gulp-load-plugins":"^1.2.0","gulp-mocha":"^2.2.0","run-sequence":"^1.1.5"},"gitHead":"03482b50129db1e057ef8d20b1a8a761b60ab179","homepage":"https://github.com/rubenjgarcia/nodesolve#readme","versions":[{"number":"0.1.0-alpha-1","date":"2016-02-19T20:19:23.121Z"}],"readme":"nodesolve\n\n[![js-standard-style](https://img.shields.io/badge/code%20style-standard-brightgreen.svg)](http://standardjs.com/)\n\nUse [LP Solve](http://lpsolve.sourceforge.net) from NodeJs. This module uses LP Solve 5.5.2\n\n# Usage\n\n**First of all, all the functions are 0-index instead of 1-index like in lpsolve**\n\nInstall the module using npm\n\n````\nnpm install nodesolve\n````\n\nFor more information see the JSDoc\n\n# Build from source\n\n1. Install node-gyp\n\n```` \nnpm install node-gyp -g\n````\n\n2. Build project files for your platform\n\n````\nnode-gyp configure\n````\n\n3. Generate `lpsolve.node` file\n\n````\nnode-gyp build\n````\n\n# Testing\n\nTo test the module use the test task from gulp\n\n````\ngulp test\n```` \n\n# Attention!!!\n\nThis module is in alpha and the following methods are **NOT** implemented yet\n\n- add_column, add_columnex, str_add_column\n- add_lag_con, str_add_lag_con\n- add_SOS\n- column_in_lp\n- copy_lp\n- default_basis\n- del_column\n- del_constraint\n- dualize_lp\n- free_lp\n- get_anti_degen\n- get_basis\n- get_basiscrash\n- get_bb_depthlimit\n- get_bb_floorfirst\n- get_bb_rule\n- get_bounds_tighter\n- get_break_at_value\n- get_col_name, get_origcol_name\n- get_column, get_columnex\n- get_constr_type\n- get_constr_value\n- get_constraints, get_ptr_constraints\n- get_epsb\n- get_epsd\n- get_epsel\n- get_epsint\n- get_epsperturb\n- get_epspivot\n- get_improve\n- get_infinite\n- get_lambda, get_ptr_lambda, get_lambda, get_ptr_lambda\n- get_lp_index\n- get_Lrows\n- get_mat\n- get_max_level, get_max_level\n- get_maxpivot\n- get_mip_gap\n- get_nameindex\n- get_negrange\n- get_nonzeros\n- get_Norig_columns\n- get_Norig_rows\n- get_obj_bound\n- get_objective\n- get_orig_index\n- get_pivoting\n- get_presolve\n- get_presolveloops\n- get_primal_solution, get_ptr_primal_solution, get_var_primalresult\n- get_print_sol\n- get_row, get_rowex\n- get_row_name, get_origrow_name\n- get_scalelimit\n- get_scaling\n- get_sensitivity_obj, get_ptr_sensitivity_obj, get_sensitivity_objex, get_ptr_sensitivity_objex\n- get_sensitivity_rhs, get_ptr_sensitivity_rhs, get_dual_solution, get_ptr_dual_solution, get_var_dualresult\n- get_simplextype\n- get_solutioncount\n- get_solutionlimit\n- get_status\n- get_statustext\n- get_total_iter\n- get_total_nodes\n- get_var_branch\n- get_var_priority, get_var_priority\n- get_variables, get_ptr_variables\n- get_working_objective\n- guess_basis\n- has_BFP\n- has_XLI\n- is_anti_degen\n- is_constr_type\n- is_debug\n- is_feasible\n- is_unbounded\n- is_infinite\n- is_integerscaling\n- is_lag_trace\n- is_nativeBFP\n- is_nativeXLI\n- is_negative\n- is_obj_in_basis\n- is_piv_mode\n- is_piv_rule\n- is_presolve\n- is_scalemode\n- is_scaletype\n- is_semicont\n- is_SOS_var\n- is_trace\n- is_use_names\n- lag_solve\n- print_constraints\n- print_debugdump\n- print_duals\n- print_lp\n- print_objective\n- print_scales\n- print_solution\n- print_str\n- print_tableau\n- put_abortfunc\n- put_bb_branchfunc\n- put_bb_nodefunc\n- put_logfunc\n- put_msgfunc\n- read_basis\n- read_mps, read_freemps, read_MPS, read_freeMPS\n- read_params\n- read_XLI\n- reset_basis\n- reset_params\n- set_anti_degen, get_anti_degen\n- set_basis\n- set_basiscrash\n- set_basisvar\n- set_bb_depthlimit\n- set_bb_floorfirst\n- set_bb_rule\n- set_BFP\n- set_XLI\n- set_bounds_tighter\n- set_break_at_value\n- set_column, set_columnex\n- set_col_name\n- set_constr_type\n- set_debug\n- set_epsb\n- set_epsd\n- set_epsel\n- set_epsint\n- set_epsperturb\n- set_epspivot\n- set_epslevel\n- set_unbounded\n- set_improve\n- set_infinite\n- set_lag_trace\n- set_mat\n- set_maxpivot\n- set_mip_gap\n- set_negrange\n- set_obj_bound\n- set_obj_in_basis\n- set_outputstream, set_outputfile\n- set_pivoting\n- set_preferdual\n- set_presolve\n- set_print_sol\n- set_row, set_rowex\n- set_row_name\n- set_scalelimit\n- set_scaling\n- set_semicont\n- set_sense\n- set_simplextype\n- set_solutionlimit\n- set_trace\n- set_use_names\n- set_var_branch\n- set_var_weights\n- time_elapsed\n- unscale\n- write_basis\n- write_mps, write_freemps, write_MPS, write_freeMPS, MPS_writefileex\n- write_params\n- write_XLI","created":"2016-02-19T20:19:23.121Z","modified":"2016-02-19T20:19:23.121Z","lastPublisher":{"name":"rubenjgarcia","email":"rubenjgarciab@gmail.com"},"owners":[{"name":"rubenjgarcia","email":"rubenjgarciab@gmail.com"}],"other":{"_attachments":{},"_from":".","_id":"nodesolve","_nodeVersion":"5.4.1","_npmOperationalInternal":{"host":"packages-9-west.internal.npmjs.com","tmp":"tmp/nodesolve-0.1.0-alpha-1.tgz_1455913158030_0.07361800060607493"},"_npmUser":{"name":"rubenjgarcia","email":"rubenjgarciab@gmail.com"},"_npmVersion":"3.3.12","_rev":"1-c09009fa7fa202b2ae54aeed954eea55","_shasum":"8992e9e59549f0f76fc6c478c704b91e546af125","author":{"name":"Ruben J Garcia","email":"rubenjgarciab@gmail.com","url":"https://github.com/rubenjgarcia"},"bugs":{"url":"https://github.com/rubenjgarcia/nodesolve/issues"},"directories":{},"dist-tags":{"latest":"0.1.0-alpha-1"},"dist":{"shasum":"8992e9e59549f0f76fc6c478c704b91e546af125","tarball":"http://registry.npmjs.org/nodesolve/-/nodesolve-0.1.0-alpha-1.tgz"},"maintainers":[{"name":"rubenjgarcia","email":"rubenjgarciab@gmail.com"}],"readmeFilename":"README.md","time":{"modified":"2016-02-19T20:19:23.121Z","created":"2016-02-19T20:19:23.121Z","0.1.0-alpha-1":"2016-02-19T20:19:23.121Z"}}}