{"name":"ocr-preprocessor","version":"0.0.8","description":"asynchronous image preprocessor based on OpenCV for OCR engine","dependencies":{"nan":"^2.0.9"},"license":"MIT","scripts":{"build":"node-gyp build","install":"node-gyp rebuild"},"keywords":["opencv","OCR","preprocessing"],"main":"./lib/ocr-preprocessor","repository":"https://github.com/Happykat/ocr-preprocessor","engines":{"node":">=0.12"},"gypfile":true,"gitHead":"8ebaf9f8137d87a4da50c13de5e00b7f50c87810","homepage":"https://github.com/Happykat/ocr-preprocessor#readme","versions":[{"number":"0.0.1","date":"2016-07-30T06:32:18.074Z"},{"number":"0.0.2","date":"2016-07-30T06:38:52.062Z"},{"number":"0.0.3","date":"2016-07-30T06:56:00.471Z"},{"number":"0.0.4","date":"2016-07-30T07:23:37.418Z"},{"number":"0.0.5","date":"2016-07-30T07:32:19.654Z"},{"number":"0.0.6","date":"2016-07-30T14:53:23.831Z"},{"number":"0.0.7","date":"2016-07-31T09:26:29.474Z"},{"number":"0.0.8","date":"2016-08-01T09:04:01.559Z"}],"readme":"# ocr-preprocessor\n\nThis is an **asynchronous** OCR **preprocessor** module for NodeJS.\n\n## Install\n\nUse npm to install it by running :\n\n```sh\nnpm install --save ocr-preprocessor\n```\n\nNote : This module is only compatible with **Linux** and **OpenCV 2.X**\n\n## Usage\n\n### Require the package \n\n```js\nvar preprocessor = require(\"ocr-preprocessor\");\n```\n\n### Use it on the image you want to process\n\n```js\nlet options = \n{ \n    blur: 3 , \n    threshold: 255 ,\n    matrix: 7 ,\n    constant: 5  \n};\n              \npreprocessor(\"./test.jpg\" , \"./result.jpg\" , options , function(err , path) {\n  if (err) {\n    console.log(\"Error !\");\n  }\n  else {\n    console.log(\"Preprocessed Image saved at : \" + path);\n  }\n});\n```\n\n## Exports\n\nThis module export itself as a single function \n\nThis function accept 4 arguments : \n\n| Argument        |                 Description             |   Type    |\n| -------------   |:---------------------------------------:|:---------:|\n| Input Path      | Path to the source image                | String    |\n| Output Path     | Path to the destination image           | String    |\n| Options         | Options passed to preprocessing engine  | Object    |\n| Callback        | Callback executed on return             | Function  |\n\n\n### Options\n\n|     Option    |           Description             |   Type    | Default |\n| ------------- |:---------------------------------:|:---------:|:-------:|\n| blur          |  Blur value                       | Number    |   0     |\n| threshold     |  Threshold value                  | Number    |  255    |\n| matrix        |  Threshold matrix size            | Number    |  3      |\n| constant      |  Threshold constant               | Number    |  5      |\n| revert        |  Revert the image                 | Boolean   |  false  |\n| isolate       |  Find and isolate biggest area    | Boolean   |  false  |\n| deskew        |  Run deskew algorithm             | Boolean   |  false  |\n| matchCount    |  Deskew sensibility               | Number    |  100    |\n| ratio         |  Line width threshold for deskew  | Number    |  2      |\n| lineStep      |  Minimum line spacing for deskew  | Number    |  20     |\n\nNote : ratio is used this way inside of the module :\n\n```c++\nimage.width() / ratio;\n```\n\nTherefore , to select lined that are half the width of the image , ratio should be set to 2.\n\n## Asynchronous\n\nThis module is asynchronous. All the work is done outside of the node main loop. It allows you to preprocess a big amount\nof images at the same time.\n","created":"2016-07-30T06:32:18.074Z","modified":"2016-08-01T09:04:01.559Z","lastPublisher":{"name":"happykat","email":"hector.roussille@gmail.com"},"owners":[{"name":"happykat","email":"hector.roussille@gmail.com"}],"other":{"_attachments":{},"_from":".","_id":"ocr-preprocessor","_nodeVersion":"6.3.1","_npmOperationalInternal":{"host":"packages-12-west.internal.npmjs.com","tmp":"tmp/ocr-preprocessor-0.0.8.tgz_1470042239561_0.5210075210779905"},"_npmUser":{"name":"happykat","email":"hector.roussille@gmail.com"},"_npmVersion":"3.10.5","_rev":"1-390c7c1a80af718fde6e07f04975e127","_shasum":"158426b762e0c61f173f7ebabf272d56ff407a63","author":{"name":"Hector Roussille","url":"hector.roussile@gmail.com"},"bugs":{"url":"https://github.com/Happykat/ocr-preprocessor/issues"},"directories":{},"dist-tags":{"latest":"0.0.8"},"dist":{"shasum":"158426b762e0c61f173f7ebabf272d56ff407a63","tarball":"http://registry.npmjs.org/ocr-preprocessor/-/ocr-preprocessor-0.0.8.tgz"},"maintainers":[{"name":"happykat","email":"hector.roussille@gmail.com"}],"readmeFilename":"README.md","time":{"modified":"2016-08-01T09:04:01.559Z","created":"2016-07-30T06:32:18.074Z","0.0.1":"2016-07-30T06:32:18.074Z","0.0.2":"2016-07-30T06:38:52.062Z","0.0.3":"2016-07-30T06:56:00.471Z","0.0.4":"2016-07-30T07:23:37.418Z","0.0.5":"2016-07-30T07:32:19.654Z","0.0.6":"2016-07-30T14:53:23.831Z","0.0.7":"2016-07-31T09:26:29.474Z","0.0.8":"2016-08-01T09:04:01.559Z"}}}