{"name":"temprepose","version":"1.0.10","description":"demo of package json","main":"lib/odbc.js","scripts":{"install":"node-pre-gyp install --fallback-to-build","install_1":"echo \"Hi: no test specified\" && exit 0","test":"echo \"Hi: no test specified\" && exit 0"},"binary":{"module_name":"odbc_bindings","module_path":"./build/","host":"https://dmphhhdczacc8.cloudfront.net/","remote_path":".","package_name":"{node_abi}-{platform}-{arch}.tar.gz"},"repository":"https://github.com/upasanag/tempRepose","dependencies":{"bindings":"^1.2.1","nan":"^2.0.9"},"license":"ISC","homepage":"https://github.com/upasanag/tempRepose#readme","gitHead":"30d290072c9cf1116f69c97b1b9f0d2646c222dd","versions":[{"number":"1.0.0","date":"2016-04-14T09:24:39.473Z"},{"number":"1.0.1","date":"2016-04-14T09:52:31.566Z"},{"number":"1.0.2","date":"2016-04-14T09:58:18.978Z"},{"number":"1.0.3","date":"2016-04-14T10:06:13.658Z"},{"number":"1.0.4","date":"2016-04-14T11:00:33.507Z"},{"number":"1.0.5","date":"2016-06-17T06:05:17.658Z"},{"number":"1.0.6","date":"2016-06-17T06:26:19.258Z"},{"number":"1.0.7","date":"2016-06-17T07:17:33.347Z"},{"number":"1.0.8","date":"2016-06-20T06:00:16.170Z"},{"number":"1.0.9","date":"2016-06-20T06:14:35.549Z"},{"number":"1.0.10","date":"2016-06-20T08:48:03.387Z"}],"readme":"NOTE\r\n---------\r\nHello\r\nWork in Progress\r\n","created":"2016-04-14T09:24:39.473Z","modified":"2016-06-20T08:48:03.387Z","lastPublisher":{"name":"upasanag","email":"upasana.gaikwad@gmail.com"},"owners":[{"name":"upasanag","email":"upasana.gaikwad@gmail.com"}],"other":{"_attachments":{},"_from":".","_id":"temprepose","_nodeVersion":"5.5.0","_npmOperationalInternal":{"host":"packages-12-west.internal.npmjs.com","tmp":"tmp/temprepose-1.0.10.tgz_1466412482939_0.0599165593739599"},"_npmUser":{"name":"upasanag","email":"upasana.gaikwad@gmail.com"},"_npmVersion":"3.5.3","_rev":"1-072af4d26b460145eb563118644846c1","_shasum":"98ccee442ac7f92ac08fb5e6df91984136592e75","author":{"name":"Upasana","email":"upasana.gaikwad@sap.com"},"bugs":{"url":"https://github.com/upasanag/tempRepose/issues"},"directories":{"lib":"."},"dist-tags":{"latest":"1.0.10"},"dist":{"shasum":"98ccee442ac7f92ac08fb5e6df91984136592e75","tarball":"http://registry.npmjs.org/temprepose/-/temprepose-1.0.10.tgz"},"maintainers":[{"name":"upasanag","email":"upasana.gaikwad@gmail.com"}],"readmeFilename":"README.md","time":{"modified":"2016-06-20T08:48:03.387Z","created":"2016-04-14T09:24:39.473Z","1.0.0":"2016-04-14T09:24:39.473Z","1.0.1":"2016-04-14T09:52:31.566Z","1.0.2":"2016-04-14T09:58:18.978Z","1.0.3":"2016-04-14T10:06:13.658Z","1.0.4":"2016-04-14T11:00:33.507Z","1.0.5":"2016-06-17T06:05:17.658Z","1.0.6":"2016-06-17T06:26:19.258Z","1.0.7":"2016-06-17T07:17:33.347Z","1.0.8":"2016-06-20T06:00:16.170Z","1.0.9":"2016-06-20T06:14:35.549Z","1.0.10":"2016-06-20T08:48:03.387Z"}}}