{"name":"windows-notification-state","version":"1.3.0","description":"SHQueryUserNotificationState as a native Node addon","main":"lib/index.js","scripts":{"test":"standard && mocha ./test/test.js","install":"node-gyp rebuild"},"repository":"https://github.com/felixrieseberg/windows-notification-state","license":"MIT","licenses":[{"type":"MIT","url":"http://github.com/felixrieseberg/windows-notification-state/blob/master/LICENSE"}],"dependencies":{"bindings":"^1.2.1","nan":"^2.4.0"},"keywords":["windows","SHQueryUserNotificationState","notifications"],"devDependencies":{"mocha":"^3.2.0","standard":"^9.0.1"},"gypfile":true,"gitHead":"a533e2b2a917fa40ecd9372fc4eb378ecda72ab5","homepage":"https://github.com/felixrieseberg/windows-notification-state#readme","versions":[{"number":"1.1.0","date":"2017-03-17T18:32:24.469Z"},{"number":"1.2.0","date":"2017-03-23T18:46:53.815Z"},{"number":"1.2.1","date":"2017-03-23T19:39:58.953Z"},{"number":"1.2.2","date":"2017-03-23T19:45:50.764Z"},{"number":"1.3.0","date":"2017-03-23T19:49:07.292Z"}],"readme":"## windows-notification-state\n[SHQueryUserNotificationState](https://msdn.microsoft.com/en-us/library/windows/desktop/bb762242(v=vs.85).aspx), implemented as a native Node addon. If you're looking for a simple solution to check whether or not you should send your user a notification, this is it.\n\n```\nnpm install windows-notification-state\n```\n\n```\nconst { shQueryUserNotificationState, getNotificationState } = require('windows-quiet-hours`)\n\n// This will print a number (corresponding with QUERY_USER_NOTIFICATION_STATE)\nconsole.log(shQueryUserNotificationState())\n\n// If you prefer your code to be more readable, you can use the string-based variant.\n// This will print the name of the enum (so \"QUNS_ACCEPTS_NOTIFICATIONS\" instead of 5)\nconsole.log(getNotificationState())\n```\n\n#### License\nMIT, please see LICENSE for details. Copyright (c) 2017 Felix Rieseberg.\n","created":"2017-03-17T18:32:24.469Z","modified":"2017-03-23T19:49:07.292Z","lastPublisher":{"name":"felixrieseberg","email":"felix@felixrieseberg.com"},"owners":[{"name":"felixrieseberg","email":"felix@felixrieseberg.com"}],"other":{"_attachments":{},"_from":".","_id":"windows-notification-state","_nodeVersion":"7.4.0","_npmOperationalInternal":{"host":"packages-12-west.internal.npmjs.com","tmp":"tmp/windows-notification-state-1.3.0.tgz_1490298547056_0.3911883549299091"},"_npmUser":{"name":"felixrieseberg","email":"felix@felixrieseberg.com"},"_npmVersion":"4.0.5","_rev":"5-0e771ec77288964920cfb50f6dff5d7e","_shasum":"9f727782ecac8d920a408f1026be6f8e08fd902e","author":{"name":"Felix Rieseberg","email":"felix@felixrieseberg.com","url":"http://www.felixrieseberg.com"},"bugs":{"url":"https://github.com/felixrieseberg/windows-notification-state/issues"},"directories":{},"dist-tags":{"latest":"1.3.0"},"dist":{"shasum":"9f727782ecac8d920a408f1026be6f8e08fd902e","tarball":"https://registry.npmjs.org/windows-notification-state/-/windows-notification-state-1.3.0.tgz"},"maintainers":[{"name":"felixrieseberg","email":"felix@felixrieseberg.com"}],"readmeFilename":"README.md","time":{"modified":"2017-03-23T19:49:07.292Z","created":"2017-03-17T18:32:24.469Z","1.1.0":"2017-03-17T18:32:24.469Z","1.2.0":"2017-03-23T18:46:53.815Z","1.2.1":"2017-03-23T19:39:58.953Z","1.2.2":"2017-03-23T19:45:50.764Z","1.3.0":"2017-03-23T19:49:07.292Z"}}}